yaml_json_diff/__init__.py
yaml_json_diff/ai_explainer.py
yaml_json_diff/cli.py
yaml_json_diff/diff.py
cloud_diff-0.1.0.dist-info/LICENSE
cloud_diff-0.1.0.dist-info/METADATA
cloud_diff-0.1.0.dist-info/WHEEL
cloud_diff-0.1.0.dist-info/entry_points.txt
cloud_diff-0.1.0.dist-info/RECORD
