Metadata-Version: 2.3
Name: cloud-diff
Version: 0.1.0
Summary: A diff tool for checking the Yaml, Json files while developing cloud based applications
License: GNU LESSER GENERAL PUBLIC LICENSE
Author: Pooya Rostami Mazrae
Requires-Python: >=3.9
Classifier: License :: Other/Proprietary License
Classifier: Programming Language :: Python :: 3
Classifier: Programming Language :: Python :: 3.9
Classifier: Programming Language :: Python :: 3.10
Classifier: Programming Language :: Python :: 3.11
Classifier: Programming Language :: Python :: 3.12
Classifier: Programming Language :: Python :: 3.13
Requires-Dist: deepdiff (>=8.5.0,<9.0.0)
Requires-Dist: pyyaml (>=6.0.2,<7.0.0)
Requires-Dist: rich (>=14.0.0,<15.0.0)
Requires-Dist: typer (>=0.16.0,<0.17.0)
